easypaystack/__init__.py
easypaystack/config.py
easypaystack/error_handler.py
easypaystack/getters.py
easypaystack/helper.py
easypaystack/payment.py
easypaystack/transfers.py
easypaystack/verification.py
easypaystack-1.1.0.dist-info/LICENSE
easypaystack-1.1.0.dist-info/METADATA
easypaystack-1.1.0.dist-info/WHEEL
easypaystack-1.1.0.dist-info/top_level.txt
easypaystack-1.1.0.dist-info/RECORD
