Metadata-Version: 2.1
Name: easypaystack
Version: 1.1.0
Summary: An easy to use python sdk for interacting with paystack
Home-page: https://github.com/i-wizard/easypaystack
Author: David Njoagwuani
Author-email: njoagwuanidavid@gmail.com
Keywords: python,paystack,easypaystack,payment,fintech,transaction
Classifier: Development Status :: 3 - Alpha
Classifier: Intended Audience :: Education
Classifier: Programming Language :: Python :: 2
Classifier: Programming Language :: Python :: 3
Classifier: Operating System :: MacOS :: MacOS X
Classifier: Operating System :: Microsoft :: Windows
License-File: LICENSE
Requires-Dist: requests
